LICENSE
MANIFEST.in
README.md
setup.cfg
setup.py
cpu/compat.h
cpu/spspmm.cpp
cuda/compat.cuh
cuda/spspmm.cpp
cuda/spspmm_kernel.cu
cuda/unique.cpp
cuda/unique_kernel.cu
test/__init__.py
test/test_coalesce.py
test/test_convert.py
test/test_eye.py
test/test_spmm.py
test/test_spspmm.py
test/test_spspmm_spmm.py
test/test_transpose.py
test/utils.py
torch_sparse/__init__.py
torch_sparse/coalesce.py
torch_sparse/convert.py
torch_sparse/eye.py
torch_sparse/spmm.py
torch_sparse/spspmm.py
torch_sparse/transpose.py
torch_sparse/utils/__init__.py
torch_sparse/utils/unique.py
torch_sparse_0.4.4.egg-info/PKG-INFO
torch_sparse_0.4.4.egg-info/SOURCES.txt
torch_sparse_0.4.4.egg-info/dependency_links.txt
torch_sparse_0.4.4.egg-info/requires.txt
torch_sparse_0.4.4.egg-info/top_level.txt